LICENSE
README.md
setup.py
tweetfinder/__init__.py
tweetfinder/article.py
tweetfinder/language.py
tweetfinder/mentions.py
tweetfinder.egg-info/PKG-INFO
tweetfinder.egg-info/SOURCES.txt
tweetfinder.egg-info/dependency_links.txt
tweetfinder.egg-info/not-zip-safe
tweetfinder.egg-info/requires.txt
tweetfinder.egg-info/top_level.txt
tweetfinder/data/twitter-patterns-rony-2018.txt
tweetfinder/test/__init__.py
tweetfinder/test/test_article.py
tweetfinder/test/test_language.py