Metadata-Version: 2.1
Name: tweetfinder
Version: 1.1.0
Summary: Find tweets embedded and mentioned in news articles online.
Author: Rahul Bhargava
Author-email: r.bhargava@northeastern.edu
License: Apache
Project-URL: Source, https://github.com/dataculturegroup/Tweet-Finder
Project-URL: Docs, https://tweet-finder.readthedocs.io/
License-File: LICENSE
Requires-Dist: requests
Requires-Dist: readability-lxml==0.8.1
Requires-Dist: py3langid==0.3.*
Requires-Dist: beautifulsoup4==4.12.*
Requires-Dist: lxml_html_clean==0.4.*
